{"currentseason":74,"league":[{"eventscores":83089,"founded":"2009-10-07T10:26:05+02:00","lastseason":74,"nationid":21,"points":2622.5,"seasons":41,"teamid":34329,"teamname":"Andrew United"},{"eventscores":81122,"founded":"2007-11-23T14:27:12+01:00","lastseason":74,"nationid":15,"points":2421.5,"seasons":45,"teamid":8585,"teamname":"Guanacos"},{"eventscores":61716,"founded":"2007-07-06T00:43:01+02:00","lastseason":74,"nationid":11,"points":1560,"seasons":36,"teamid":4339,"teamname":"Caledonian"},{"eventscores":49574,"founded":"2009-10-25T22:05:02+01:00","lastseason":67,"nationid":16,"points":1548.5,"seasons":23,"teamid":34989,"teamname":"Apex Athletics"},{"eventscores":42490,"founded":"2013-03-08T14:44:50+01:00","lastseason":74,"nationid":11,"points":1234.5,"seasons":22,"teamid":71602,"teamname":"Loughborough Harriers"},{"eventscores":40503,"founded":"2014-01-06T22:51:45+01:00","lastseason":74,"nationid":51,"points":1193,"seasons":21,"teamid":76765,"teamname":"Quantum TC"},{"eventscores":36982,"founded":"2007-09-16T13:46:57+02:00","lastseason":49,"nationid":14,"points":1082.5,"seasons":20,"teamid":6921,"teamname":"Antequera"},{"eventscores":41889,"founded":"2008-03-10T10:54:04+01:00","lastseason":74,"nationid":3,"points":1012,"seasons":24,"teamid":11791,"teamname":"Mallen IF"},{"eventscores":35179,"founded":"2010-05-30T12:44:42+02:00","lastseason":61,"nationid":11,"points":1004.5,"seasons":19,"teamid":43792,"teamname":"JLR"},{"eventscores":33453,"founded":"2011-09-30T09:41:47+02:00","lastseason":74,"nationid":33,"points":995.5,"seasons":18,"teamid":58741,"teamname":"Ragnar"},{"eventscores":34027,"founded":"2007-02-16T19:02:39+01:00","lastseason":47,"nationid":2,"points":951,"seasons":19,"teamid":2389,"teamname":"Running Gag"},{"eventscores":35025,"founded":"2010-08-29T19:55:57+02:00","lastseason":64,"nationid":11,"points":863.5,"seasons":20,"teamid":47606,"teamname":"Croydon Harriers"},{"eventscores":27765,"founded":"2009-11-27T00:09:05+01:00","lastseason":74,"nationid":27,"points":830,"seasons":15,"teamid":36098,"teamname":"Usain Bolt"},{"eventscores":25260,"founded":"2010-10-26T21:11:33+02:00","lastseason":74,"nationid":52,"points":804,"seasons":12,"teamid":49572,"teamname":"Ballyfin"},{"eventscores":24977,"founded":"2008-08-27T23:40:40+02:00","lastseason":42,"nationid":25,"points":680,"seasons":13,"teamid":18482,"teamname":"Club Atletico guthrix"},{"eventscores":21832,"founded":"2012-07-29T00:06:39+02:00","lastseason":56,"nationid":11,"points":615.5,"seasons":11,"teamid":65015,"teamname":"Dobcross"},{"eventscores":22382,"founded":"2010-10-04T21:10:25+02:00","lastseason":65,"nationid":11,"points":573.5,"seasons":14,"teamid":48834,"teamname":"Geordie Magpies"},{"eventscores":22656,"founded":"2011-01-12T15:11:08+01:00","lastseason":74,"nationid":3,"points":540,"seasons":16,"teamid":52180,"teamname":"Zico"},{"eventscores":16237,"founded":"2008-05-15T17:15:46+02:00","lastseason":36,"nationid":26,"points":512.5,"seasons":8,"teamid":13876,"teamname":"haitun"},{"eventscores":16673,"founded":"2007-12-29T13:14:52+01:00","lastseason":38,"nationid":10,"points":506,"seasons":10,"teamid":9668,"teamname":"Houston Rockets"},{"eventscores":15195,"founded":"2008-12-13T19:15:59+01:00","lastseason":45,"nationid":15,"points":471,"seasons":8,"teamid":22819,"teamname":"vicente ferrety"},{"eventscores":19758,"founded":"2014-01-26T14:58:54+01:00","lastseason":70,"nationid":60,"points":465,"seasons":12,"teamid":77207,"teamname":"Kenya Runners"},{"eventscores":17865,"founded":"2009-04-02T09:09:54+02:00","lastseason":58,"nationid":42,"points":391,"seasons":11,"teamid":26738,"teamname":"_Lviv_"},{"eventscores":16910,"founded":"2013-06-30T16:01:56+02:00","lastseason":69,"nationid":60,"points":387.5,"seasons":10,"teamid":73632,"teamname":"Brest"},{"eventscores":13739,"founded":"2010-08-01T17:40:10+02:00","lastseason":47,"nationid":49,"points":375,"seasons":9,"teamid":46262,"teamname":"Black Kiwis"},{"eventscores":13960,"founded":"2011-05-20T01:04:12+02:00","lastseason":61,"nationid":41,"points":371.5,"seasons":10,"teamid":55281,"teamname":"WHAC"},{"eventscores":13600,"founded":"2014-12-20T16:54:17+01:00","lastseason":70,"nationid":67,"points":365,"seasons":8,"teamid":80440,"teamname":"LeanBody Perform"},{"eventscores":11765,"founded":"2007-05-30T21:52:35+02:00","lastseason":35,"nationid":2,"points":352,"seasons":6,"teamid":3644,"teamname":"Beenz"},{"eventscores":14585,"founded":"2010-07-30T22:08:55+02:00","lastseason":72,"nationid":9,"points":347,"seasons":9,"teamid":46151,"teamname":"Silkeborg AK"},{"eventscores":16645,"founded":"2008-04-22T05:42:40+02:00","lastseason":62,"nationid":25,"points":338.5,"seasons":12,"teamid":13111,"teamname":"crxzadictos"},{"eventscores":11166,"founded":"2012-08-19T19:20:02+02:00","lastseason":62,"nationid":52,"points":338,"seasons":6,"teamid":66276,"teamname":"Kellys Corkers"},{"eventscores":13769,"founded":"2008-09-13T02:00:19+02:00","lastseason":52,"nationid":11,"points":320,"seasons":9,"teamid":19628,"teamname":"ACK KRIVAN"},{"eventscores":13607,"founded":"2012-07-31T12:51:16+02:00","lastseason":65,"nationid":11,"points":320,"seasons":10,"teamid":64978,"teamname":"Humbugs"},{"eventscores":10889,"founded":"2008-02-13T17:20:23+01:00","lastseason":40,"nationid":19,"points":301,"seasons":7,"teamid":11094,"teamname":"Green and Gold"},{"eventscores":10647,"founded":"2008-09-06T03:36:15+02:00","lastseason":41,"nationid":19,"points":298,"seasons":6,"teamid":19067,"teamname":"U of S Huskies"},{"eventscores":11421,"founded":"2008-01-10T03:17:59+01:00","lastseason":38,"nationid":17,"points":293.5,"seasons":7,"teamid":9963,"teamname":"Macanudos AC"},{"eventscores":8919,"founded":"2008-10-16T18:37:21+02:00","lastseason":34,"nationid":30,"points":278,"seasons":6,"teamid":20843,"teamname":"ASC Sprint"},{"eventscores":10025,"founded":"2013-01-16T12:25:56+01:00","lastseason":74,"nationid":3,"points":276,"seasons":6,"teamid":70415,"teamname":"Mediummen"},{"eventscores":12015,"founded":"2007-07-05T16:27:08+02:00","lastseason":48,"nationid":11,"points":264.5,"seasons":8,"teamid":4248,"teamname":"Iron Road Runners"},{"eventscores":11915,"founded":"2011-08-31T12:03:14+02:00","lastseason":66,"nationid":2,"points":251,"seasons":8,"teamid":57992,"teamname":"Paso Team"},{"eventscores":9540,"founded":"2013-02-16T21:52:54+01:00","lastseason":49,"nationid":10,"points":243,"seasons":6,"teamid":71042,"teamname":"Transylvania Talents"},{"eventscores":11387,"founded":"2009-03-26T21:21:45+01:00","lastseason":74,"nationid":41,"points":236,"seasons":8,"teamid":26560,"teamname":"Ecseri Meteor SK"},{"eventscores":8328,"founded":"2008-02-14T16:04:52+01:00","lastseason":34,"nationid":19,"points":229,"seasons":6,"teamid":11119,"teamname":"Flying M Athletic Club"},{"eventscores":9988,"founded":"2014-01-15T09:58:05+01:00","lastseason":74,"nationid":42,"points":227,"seasons":7,"teamid":76875,"teamname":"sport for life"},{"eventscores":8563,"founded":"2012-02-13T21:57:41+01:00","lastseason":51,"nationid":11,"points":216.5,"seasons":5,"teamid":61374,"teamname":"Hamilton Invaders"},{"eventscores":8333,"founded":"2010-10-15T01:06:46+02:00","lastseason":45,"nationid":29,"points":211,"seasons":6,"teamid":49244,"teamname":"Dalmaria Athletics"},{"eventscores":8973,"founded":"2008-10-12T11:31:57+02:00","lastseason":60,"nationid":28,"points":206,"seasons":7,"teamid":20704,"teamname":"VK78"},{"eventscores":8368,"founded":"2007-11-24T02:55:18+01:00","lastseason":36,"nationid":17,"points":202,"seasons":5,"teamid":8616,"teamname":"Clube Atletico Capixaba"},{"eventscores":7374,"founded":"2014-08-15T19:41:22+02:00","lastseason":70,"nationid":17,"points":201,"seasons":4,"teamid":79424,"teamname":"The Hunters A.C"},{"eventscores":8443,"founded":"2015-11-06T00:11:51+01:00","lastseason":69,"nationid":51,"points":176,"seasons":5,"teamid":83430,"teamname":"OPV Athletics"},{"eventscores":6989,"founded":"2008-06-21T15:28:29+02:00","lastseason":44,"nationid":17,"points":172.5,"seasons":4,"teamid":15139,"teamname":"Mineiros Esporte Clube"},{"eventscores":7610,"founded":"2007-04-26T19:52:05+02:00","lastseason":38,"nationid":3,"points":158.5,"seasons":5,"teamid":2792,"teamname":"Abacus"},{"eventscores":5402,"founded":"2008-09-09T01:01:06+02:00","lastseason":32,"nationid":31,"points":156,"seasons":4,"teamid":19321,"teamname":"Askatasuna"},{"eventscores":4786,"founded":"2011-08-05T14:53:28+02:00","lastseason":45,"nationid":28,"points":136,"seasons":3,"teamid":57369,"teamname":"Paja"},{"eventscores":5284,"founded":"2010-01-05T15:40:55+01:00","lastseason":36,"nationid":46,"points":127.5,"seasons":3,"teamid":38496,"teamname":"Nordby Idrettslag"},{"eventscores":4182,"founded":"2009-03-16T16:56:05+01:00","lastseason":30,"nationid":10,"points":125,"seasons":2,"teamid":26303,"teamname":"Rapid Gunners"},{"eventscores":4432,"founded":"2015-11-26T06:21:58+01:00","lastseason":71,"nationid":8,"points":95,"seasons":3,"teamid":83525,"teamname":"Tallinna Devils"},{"eventscores":3766,"founded":"2015-02-07T00:02:01+01:00","lastseason":71,"nationid":8,"points":90.5,"seasons":2,"teamid":80980,"teamname":"Nõmmme KJK"},{"eventscores":4577,"founded":"2010-08-31T14:35:20+02:00","lastseason":45,"nationid":9,"points":89,"seasons":3,"teamid":47539,"teamname":"Sprinters"},{"eventscores":4092,"founded":"2008-02-05T08:04:40+01:00","lastseason":55,"nationid":22,"points":86,"seasons":3,"teamid":10841,"teamname":"TJ Ab ovo Bardejov"},{"eventscores":3367,"founded":"2010-02-16T15:28:01+01:00","lastseason":42,"nationid":15,"points":76.5,"seasons":3,"teamid":40487,"teamname":"Kapanga"},{"eventscores":4316,"founded":"2010-02-16T08:56:47+01:00","lastseason":66,"nationid":41,"points":74,"seasons":3,"teamid":40476,"teamname":"Sprint Club"},{"eventscores":3788,"founded":"2010-01-05T16:35:57+01:00","lastseason":73,"nationid":48,"points":73,"seasons":2,"teamid":38829,"teamname":"1312"},{"eventscores":2949,"founded":"2011-07-19T15:46:24+02:00","lastseason":47,"nationid":24,"points":71,"seasons":2,"teamid":56926,"teamname":"Negros Celestes AC"},{"eventscores":2889,"founded":"2009-04-15T07:43:52+02:00","lastseason":30,"nationid":30,"points":68,"seasons":2,"teamid":27232,"teamname":"AFC Twix"},{"eventscores":3254,"founded":"2007-07-22T23:13:40+02:00","lastseason":33,"nationid":11,"points":62.5,"seasons":2,"teamid":4963,"teamname":"Romford Runners"},{"eventscores":2852,"founded":"2009-05-20T00:23:55+02:00","lastseason":35,"nationid":17,"points":61,"seasons":3,"teamid":28004,"teamname":"Atletico Bulls"},{"eventscores":2329,"founded":"2008-12-14T20:18:34+01:00","lastseason":30,"nationid":27,"points":57,"seasons":2,"teamid":22858,"teamname":"The Hills"},{"eventscores":2660,"founded":"2008-02-23T18:35:18+01:00","lastseason":45,"nationid":10,"points":54,"seasons":2,"teamid":11362,"teamname":"Atletico Addarts"},{"eventscores":2127,"founded":"2011-11-17T16:58:44+01:00","lastseason":47,"nationid":52,"points":53.5,"seasons":2,"teamid":59650,"teamname":"ATPKERRY"},{"eventscores":2888,"founded":"2015-07-03T08:38:43+02:00","lastseason":67,"nationid":64,"points":53,"seasons":2,"teamid":82336,"teamname":"Perenkopf"},{"eventscores":1900,"founded":"2012-01-03T15:46:32+01:00","lastseason":37,"nationid":10,"points":51,"seasons":1,"teamid":60565,"teamname":"Rapid Gunners Reloaded"},{"eventscores":2495,"founded":"2018-03-01T14:21:36+01:00","lastseason":74,"nationid":11,"points":43.5,"seasons":2,"teamid":87985,"teamname":"Hamilton Stampede"},{"eventscores":1721,"founded":"2010-07-28T11:00:16+02:00","lastseason":37,"nationid":11,"points":38,"seasons":1,"teamid":45779,"teamname":"Leicester Coritanian"},{"eventscores":2349,"founded":"2009-04-06T20:13:06+02:00","lastseason":37,"nationid":30,"points":37,"seasons":2,"teamid":26919,"teamname":"LC Perchtoldsdorf"},{"eventscores":1632,"founded":"2012-12-05T03:13:26+01:00","lastseason":71,"nationid":17,"points":34,"seasons":1,"teamid":69329,"teamname":"Javorski"},{"eventscores":2580,"founded":"2011-09-07T16:05:26+02:00","lastseason":74,"nationid":42,"points":32.5,"seasons":3,"teamid":58303,"teamname":"Kharkov Tigers"},{"eventscores":1576,"founded":"2014-09-25T12:10:03+02:00","lastseason":61,"nationid":28,"points":31,"seasons":1,"teamid":79915,"teamname":"Champions"},{"eventscores":1573,"founded":"","lastseason":37,"nationid":0,"points":29,"seasons":1,"teamid":25774,"teamname":"Unknown team from Shanghai China"},{"eventscores":2361,"founded":"2008-03-31T19:58:46+02:00","lastseason":73,"nationid":11,"points":28.5,"seasons":2,"teamid":12304,"teamname":"Olympians"},{"eventscores":1564,"founded":"2007-07-07T12:41:48+02:00","lastseason":34,"nationid":8,"points":28,"seasons":1,"teamid":4546,"teamname":"Reinhard"},{"eventscores":1468,"founded":"2009-08-27T21:29:03+02:00","lastseason":32,"nationid":38,"points":27.5,"seasons":1,"teamid":32477,"teamname":"TJ Sršeň Srch"},{"eventscores":1628,"founded":"2008-11-01T17:01:40+01:00","lastseason":30,"nationid":25,"points":26,"seasons":1,"teamid":21401,"teamname":"Hurdlevils AC"},{"eventscores":1480,"founded":"2012-04-03T12:48:00+02:00","lastseason":56,"nationid":11,"points":26,"seasons":1,"teamid":62424,"teamname":"Jackdaw AC"},{"eventscores":1465,"founded":"2009-12-31T10:50:07+01:00","lastseason":36,"nationid":48,"points":24,"seasons":1,"teamid":38349,"teamname":"Bijok Musu"},{"eventscores":1416,"founded":"2009-01-15T22:20:51+01:00","lastseason":31,"nationid":38,"points":24,"seasons":1,"teamid":23794,"teamname":"AK Havran Mirova"},{"eventscores":1164,"founded":"2007-12-27T10:40:23+01:00","lastseason":29,"nationid":10,"points":24,"seasons":1,"teamid":9506,"teamname":"Gabi Club"},{"eventscores":1169,"founded":"2009-08-17T16:40:01+02:00","lastseason":32,"nationid":38,"points":23,"seasons":1,"teamid":31362,"teamname":"AK VIGO Drnovice"},{"eventscores":1790,"founded":"2015-07-24T20:57:06+02:00","lastseason":74,"nationid":17,"points":22,"seasons":2,"teamid":82568,"teamname":"Brasília Athletics"},{"eventscores":1134,"founded":"2011-01-28T22:18:21+01:00","lastseason":53,"nationid":15,"points":22,"seasons":1,"teamid":52612,"teamname":"Atenas"},{"eventscores":1246,"founded":"2007-07-05T20:18:46+02:00","lastseason":49,"nationid":11,"points":21,"seasons":1,"teamid":4289,"teamname":"Harefield Harriors"},{"eventscores":1195,"founded":"2014-02-26T04:43:20+01:00","lastseason":73,"nationid":19,"points":20,"seasons":1,"teamid":77679,"teamname":"Titans"},{"eventscores":952,"founded":"2007-12-12T01:08:15+01:00","lastseason":29,"nationid":10,"points":20,"seasons":1,"teamid":9178,"teamname":"Nextnet Arad"},{"eventscores":1182,"founded":"2014-09-08T19:34:19+02:00","lastseason":58,"nationid":11,"points":19,"seasons":1,"teamid":79776,"teamname":"Iddesleigh Athletic"},{"eventscores":1118,"founded":"2010-07-01T11:02:38+02:00","lastseason":41,"nationid":46,"points":19,"seasons":1,"teamid":44937,"teamname":"Care production"},{"eventscores":1342,"founded":"2013-04-26T01:13:47+02:00","lastseason":65,"nationid":17,"points":18,"seasons":1,"teamid":72553,"teamname":"Sem limites"},{"eventscores":1119,"founded":"2014-09-10T15:15:52+02:00","lastseason":60,"nationid":11,"points":18,"seasons":1,"teamid":79790,"teamname":"North Devon"},{"eventscores":1109,"founded":"2009-04-23T15:58:40+02:00","lastseason":31,"nationid":41,"points":18,"seasons":1,"teamid":27450,"teamname":"Flying Cats"},{"eventscores":1082,"founded":"2009-01-04T22:20:14+01:00","lastseason":54,"nationid":19,"points":18,"seasons":1,"teamid":23437,"teamname":"Coureurs de Bois"},{"eventscores":1051,"founded":"2009-11-21T15:44:23+01:00","lastseason":61,"nationid":19,"points":18,"seasons":1,"teamid":35965,"teamname":"Team Gecko"},{"eventscores":685,"founded":"2008-01-18T21:30:08+01:00","lastseason":29,"nationid":10,"points":17,"seasons":1,"teamid":10202,"teamname":"FC Darko 1921 Timisoara"},{"eventscores":1346,"founded":"2010-07-29T13:52:02+02:00","lastseason":73,"nationid":3,"points":16,"seasons":1,"teamid":46030,"teamname":"Bjornhojden"},{"eventscores":1107,"founded":"2011-07-06T20:47:13+02:00","lastseason":56,"nationid":11,"points":16,"seasons":1,"teamid":56585,"teamname":"Ardler Athletics Association"},{"eventscores":711,"founded":"2011-07-13T22:08:08+02:00","lastseason":57,"nationid":15,"points":14,"seasons":1,"teamid":56782,"teamname":"Los Reyes de Km. 38"},{"eventscores":1062,"founded":"2012-10-01T16:08:47+02:00","lastseason":51,"nationid":11,"points":13,"seasons":1,"teamid":67853,"teamname":"Yellerbellies"},{"eventscores":582,"founded":"2012-10-27T14:41:26+02:00","lastseason":53,"nationid":40,"points":12,"seasons":1,"teamid":68372,"teamname":"AK Latkova vas"},{"eventscores":806,"founded":"2015-09-24T21:05:06+02:00","lastseason":64,"nationid":2,"points":11,"seasons":1,"teamid":83162,"teamname":"dreamliner"},{"eventscores":928,"founded":"2009-10-19T16:57:28+02:00","lastseason":37,"nationid":17,"points":9,"seasons":1,"teamid":34800,"teamname":"Mento"},{"eventscores":272,"founded":"2007-11-21T14:56:24+01:00","lastseason":29,"nationid":10,"points":9,"seasons":1,"teamid":8529,"teamname":"Mad Clopoyaurs"},{"eventscores":0,"founded":"2015-02-26T11:41:25+01:00","lastseason":68,"nationid":24,"points":0,"seasons":1,"teamid":81350,"teamname":"Chimbarongo CA"}],"timestamp":"2020-04-05 05:09:07"}