{"nationid":2,"teamdata":[{"eventscores":813,"points":22,"position":10,"season":90},{"eventscores":1845,"points":53,"position":6,"season":89},{"eventscores":1918,"points":48,"position":10,"season":88},{"eventscores":1982,"points":55,"position":2,"season":87},{"eventscores":1826,"points":45,"position":8,"season":86},{"eventscores":1893,"points":49,"position":6,"season":85},{"eventscores":1665,"points":47,"position":8,"season":84},{"eventscores":1633,"points":38,"position":11,"season":83},{"eventscores":1699,"points":43,"position":12,"season":82},{"eventscores":1776,"points":42,"position":11,"season":81},{"eventscores":1781,"points":47,"position":6,"season":80},{"eventscores":1916,"points":42,"position":11,"season":79},{"eventscores":1693,"points":47,"position":9,"season":78},{"eventscores":1858,"points":52,"position":5,"season":77},{"eventscores":1789,"points":45,"position":8,"season":76}],"teamid":86514,"teamname":"Sporting Olomouc","timestamp":"2023-05-07 05:09:23","totaleventscores":26087,"totalpoints":675}